maboss_setup.py
maboss_setup_experimental.py
maboss/__init__.py
maboss/bnetsimulation.py
maboss/cmabossresult.py
maboss/cmabossresult2.py
maboss/cmabosssimulation.py
maboss/figures.py
maboss/gsparser.py
maboss/logic.py
maboss/network.py
maboss/result.py
maboss/sbmlcmabossresult.py
maboss/sbmlsimulation.py
maboss/simulation.py
maboss/ui.py
maboss/ensemble/__init__.py
maboss/ensemble/ensemble.py
maboss/ensemble/result.py
maboss/pipelines/__init__.py
maboss/pop/__init__.py
maboss/pop/cmabosspopresult.py
maboss/pop/popresult.py
maboss/pop/popsimulation.py
maboss/pop/storedpopresult.py
maboss/results/__init__.py
maboss/results/baseresult.py
maboss/results/finalresult.py
maboss/results/probtrajresult.py
maboss/results/statdistresult.py
maboss/results/storedresult.py
maboss/server/__init__.py
maboss/server/atexit.py
maboss/server/client.py
maboss/server/comm.py
maboss/server/result.py
maboss/upp/__init__.py
maboss/upp/cmaboss_results.py
maboss/upp/results.py
maboss/upp/upp.py
maboss/widgets/__init__.py
maboss/widgets/ipywidgets.py
maboss/widgets/menu.py
maboss-0.8.12.data/scripts/MBSS_FormatTable.py
maboss-0.8.12.data/scripts/UpPMaBoSS.py
maboss-0.8.12.dist-info/METADATA
maboss-0.8.12.dist-info/WHEEL
maboss-0.8.12.dist-info/top_level.txt
maboss-0.8.12.dist-info/RECORD
