Metadata-Version: 2.1
Name: maboss
Version: 0.8.12
Summary: A python and jupyter API for the MaBoSS software
Home-page: https://maboss.curie.fr
Author: Vincent Noël, Loic Paulevé, Aurelien Naldi and Nicolas Levy
Author-email: vincent.noel@curie.fr
Requires-Dist: cmaboss >=1.0.0b30
Requires-Dist: colomoto-jupyter >=0.4.10
Requires-Dist: ipywidgets
Requires-Dist: matplotlib
Requires-Dist: networkx
Requires-Dist: pandas
Requires-Dist: pyparsing
Requires-Dist: scikit-learn
